LICENSE.txt
MANIFEST.in
README.rst
requirements.txt
setup.py
Django_Accounts.egg-info/PKG-INFO
Django_Accounts.egg-info/SOURCES.txt
Django_Accounts.egg-info/dependency_links.txt
Django_Accounts.egg-info/requires.txt
Django_Accounts.egg-info/top_level.txt
accounts/__init__.py
accounts/forms.py
accounts/models.py
accounts/settings.py
accounts/urls.py
accounts/views.py
accounts/templates/accounts/activation.html
accounts/templates/accounts/activation_email_message.html
accounts/templates/accounts/activation_email_subject.txt
accounts/templates/accounts/base.html
accounts/templates/accounts/profile_base.html
accounts/templates/accounts/profile_form.html
accounts/templates/accounts/profile_summary.html
accounts/templates/accounts/signup_form.html
accounts/templates/accounts/signup_login_form.html
accounts/templates/accounts/signup_success.html
accounts/templates/auth/logged_out.html
accounts/templates/auth/login.html
accounts/templates/auth/password_change_done.html
accounts/templates/auth/password_change_form.html
accounts/templates/auth/password_reset_complete.html
accounts/templates/auth/password_reset_confirm.html
accounts/templates/auth/password_reset_done.html
accounts/templates/auth/password_reset_email.html
accounts/templates/auth/password_reset_form.html