Metadata-Version: 1.1
Name: Django-Accounts
Version: 0.1
Summary: A batteries-included solution for Django accounts.
Home-page: https://github.com/binarybirchtree/django-accounts
Author: Binary Birch Tree
Author-email: binarybirchtree@users.noreply.github.com
License: GNU General Public License version 3
Download-URL: https://github.com/binarybirchtree/django-accounts/archive/master.zip
Platform: UNKNOWN
Classifier: Programming Language :: Python
Classifier: License :: OSI Approved :: GNU General Public License v3 or later (GPLv3+)
Classifier: Operating System :: OS Independent
Classifier: Framework :: Django
Classifier: Environment :: Web Environment
Classifier: Topic :: Internet :: WWW/HTTP
Classifier: Topic :: Software Development :: Libraries :: Python Modules
